tonutils/__init__.py
tonutils/account.py
tonutils/cache.py
tonutils/contract.py
tonutils/exceptions.py
tonutils/py.typed
tonutils/utils.py
tonutils/client/__init__.py
tonutils/client/_base.py
tonutils/client/lite.py
tonutils/client/quicknode.py
tonutils/client/tatum.py
tonutils/client/tonapi.py
tonutils/client/toncenter.py
tonutils/client/utils.py
tonutils/dns/__init__.py
tonutils/dns/categories.py
tonutils/dns/contract.py
tonutils/dns/op_codes.py
tonutils/dns/utils.py
tonutils/dns/subdomain_collection/__init__.py
tonutils/dns/subdomain_collection/content.py
tonutils/dns/subdomain_collection/contract.py
tonutils/dns/subdomain_collection/data.py
tonutils/dns/subdomain_collection/op_codes.py
tonutils/dns/subdomain_manager/__init__.py
tonutils/dns/subdomain_manager/contract.py
tonutils/dns/subdomain_manager/data.py
tonutils/dns/subdomain_manager/op_codes.py
tonutils/jetton/__init__.py
tonutils/jetton/content.py
tonutils/jetton/data.py
tonutils/jetton/contract/__init__.py
tonutils/jetton/contract/base/__init__.py
tonutils/jetton/contract/base/master.py
tonutils/jetton/contract/stablecoin/__init__.py
tonutils/jetton/contract/stablecoin/master.py
tonutils/jetton/contract/stablecoin/op_codes.py
tonutils/jetton/contract/stablecoin/wallet.py
tonutils/jetton/contract/standard/__init__.py
tonutils/jetton/contract/standard/master.py
tonutils/jetton/contract/standard/op_codes.py
tonutils/jetton/contract/standard/wallet.py
tonutils/jetton/dex/__init__.py
tonutils/jetton/dex/dedust/__init__.py
tonutils/jetton/dex/dedust/constants.py
tonutils/jetton/dex/dedust/factory.py
tonutils/jetton/dex/stonfi/__init__.py
tonutils/jetton/dex/stonfi/utils.py
tonutils/jetton/dex/stonfi/v1/__init__.py
tonutils/jetton/dex/stonfi/v1/pton/__init__.py
tonutils/jetton/dex/stonfi/v1/pton/constants.py
tonutils/jetton/dex/stonfi/v1/pton/pton.py
tonutils/jetton/dex/stonfi/v1/router/__init__.py
tonutils/jetton/dex/stonfi/v1/router/constants.py
tonutils/jetton/dex/stonfi/v1/router/router.py
tonutils-0.5.5.dist-info/licenses/LICENSE
tonutils-0.5.5.dist-info/METADATA
tonutils-0.5.5.dist-info/WHEEL
tonutils-0.5.5.dist-info/top_level.txt
tonutils-0.5.5.dist-info/RECORD
