Metadata-Version: 2.4
Name: tonutils
Version: 0.5.5
Summary: Tonutils is a high-level, object-oriented Python library designed to facilitate seamless interactions with the TON blockchain.
Author: nessshon
License: MIT
Project-URL: Homepage, https://github.com/nessshon/tonutils
Project-URL: Documentation, https://nessshon.github.io/tonutils
Project-URL: Examples, https://github.com/nessshon/tonutils/tree/main/examples
Project-URL: Source, https://github.com/nessshon/tonutils
Project-URL: TON, https://ton.org
Keywords: TON,The Open Network,TON blockchain,blockchain,crypto,asynchronous,smart contracts
Classifier: Development Status :: 4 - Beta
Classifier: Intended Audience :: Developers
Classifier: Intended Audience :: Financial and Insurance Industry
Classifier: Topic :: Software Development :: Libraries :: Python Modules
Classifier: Programming Language :: Python :: 3.10
Classifier: Programming Language :: Python :: 3.11
Classifier: Programming Language :: Python :: 3.12
Classifier: License :: OSI Approved :: MIT License
Classifier: Operating System :: OS Independent
Classifier: Framework :: AsyncIO
Classifier: Environment :: Console
Requires-Python: >=3.10
License-File: LICENSE
Requires-Dist: aiohttp<=3.12.2,>=3.7.0
Requires-Dist: aiolimiter~=1.2.1
Requires-Dist: cachetools~=5.5.0
Requires-Dist: pycryptodomex~=3.20.0
Requires-Dist: PyNaCl~=1.5.0
Requires-Dist: pytoniq-core>=0.1.45
Provides-Extra: pytoniq
Requires-Dist: pytoniq~=0.1.42; extra == "pytoniq"
Dynamic: license-file
